LICENSE
MANIFEST.in
README.md
setup.py
skrebate/__init__.py
skrebate/_version.py
skrebate/multisurf.py
skrebate/multisurfstar.py
skrebate/relieff.py
skrebate/scoring_utils.py
skrebate/surf.py
skrebate/surfstar.py
skrebate/turf.py
skrebate/vlsrelief.py
skrebate.egg-info/PKG-INFO
skrebate.egg-info/SOURCES.txt
skrebate.egg-info/dependency_links.txt
skrebate.egg-info/requires.txt
skrebate.egg-info/top_level.txt
skrebate.egg-info/zip-safe