Metadata-Version: 1.1
Name: skrebate
Version: 0.62
Summary: Relief-based feature selection algorithms
Home-page: https://github.com/EpistasisLab/scikit-rebate
Author: Randal S. Olson, Pete Schmitt, and Ryan J. Urbanowicz
Author-email: rso@randalolson.com, ryanurb@upenn.edu
License: License :: OSI Approved :: MIT License
Keywords: data mining,feature selection,feature importance,machine learning,data analysis,data engineering,data science
Platform: UNKNOWN
Classifier: Intended Audience :: Developers
Classifier: Intended Audience :: Information Technology
Classifier: Intended Audience :: Science/Research
Classifier: License :: OSI Approved :: MIT License
Classifier: Programming Language :: Python :: 2
Classifier: Programming Language :: Python :: 2.7
Classifier: Programming Language :: Python :: 3
Classifier: Programming Language :: Python :: 3.4
Classifier: Programming Language :: Python :: 3.5
Classifier: Programming Language :: Python :: 3.6
Classifier: Topic :: Utilities
